numutils/__init__.py
numutils/n2w.py
numutils/config/en.yaml
numutils.n2w-0.1.3.dist-info/LICENSE
numutils.n2w-0.1.3.dist-info/METADATA
numutils.n2w-0.1.3.dist-info/WHEEL
numutils.n2w-0.1.3.dist-info/top_level.txt
numutils.n2w-0.1.3.dist-info/RECORD
