Metadata-Version: 2.1
Name: numutils.n2w
Version: 0.1.3
Summary: Helper library that converts numbers to words
Home-page: https://github.com/gnuchu/numutils.n2w
Author: John Griffiths
Author-email: gnuchu@gmail.com
License: MIT license
Keywords: n2w
Platform: UNKNOWN
Classifier: Development Status :: 2 - Pre-Alpha
Classifier: Intended Audience :: Developers
Classifier: License :: OSI Approved :: MIT License
Classifier: Natural Language :: English
Classifier: Programming Language :: Python :: 3
Classifier: Programming Language :: Python :: 3.7
Classifier: Programming Language :: Python :: 3.8
Classifier: Programming Language :: Python :: 3.9
Classifier: Programming Language :: Python :: 3.9
Classifier: Programming Language :: Python :: 3.10
Requires-Python: >=3.7
License-File: LICENSE
Requires-Dist: pyyaml
Requires-Dist: wheel
